cronomaxrf/__init__.py
cronomaxrf/_modidx.py
cronomaxrf/_nbdev.py
cronomaxrf/crono.py
cronomaxrf/data.py
cronomaxrf/gridify.py
cronomaxrf/interpolation.py
cronomaxrf-0.0.12.dist-info/LICENSE
cronomaxrf-0.0.12.dist-info/METADATA
cronomaxrf-0.0.12.dist-info/WHEEL
cronomaxrf-0.0.12.dist-info/entry_points.txt
cronomaxrf-0.0.12.dist-info/top_level.txt
cronomaxrf-0.0.12.dist-info/RECORD
