Metadata-Version: 2.1
Name: cronomaxrf
Version: 0.0.12
Summary: Python package to read and convert the Crono MA-XRF HDF5 data file format
Home-page: https://github.com/fligt/cronomaxrf
Author: Frank Ligterink
Author-email: frank.ligterink@gmail.com
License: GNU General Public License v3
Keywords: XRF HDF5
Platform: UNKNOWN
Classifier: Development Status :: 3 - Alpha
Classifier: Intended Audience :: Developers
Classifier: Natural Language :: English
Classifier: Programming Language :: Python :: 3.7
Classifier: Programming Language :: Python :: 3.8
Classifier: Programming Language :: Python :: 3.9
Classifier: Programming Language :: Python :: 3.10
Classifier: License :: OSI Approved :: GNU General Public License v3 (GPLv3)
Requires-Python: >=3.7
Requires-Dist: h5py
Requires-Dist: dask
Requires-Dist: zarr
Requires-Dist: matplotlib
Requires-Dist: numpy
Requires-Dist: IPython
Requires-Dist: wget
Requires-Dist: dask-ndfilters
Requires-Dist: filehash
Provides-Extra: dev
Requires-Dist: matplotlib ; extra == 'dev'
